{
  "$schema": "https://developer.microsoft.com/json-schemas/fabric/item/report/definition/visualContainer/2.10.0/schema.json",
  "name": "fb722a441efb40e0c225",
  "position": {
    "x": 24,
    "y": 37,
    "z": 3013,
    "height": 20,
    "width": 500,
    "tabOrder": 3013
  },
  "visual": {
    "visualType": "textbox",
    "objects": {
      "general": [
        {
          "properties": {
            "paragraphs": [
              {
                "textRuns": [
                  {
                    "value": "공동주택 관리비 이상징후 및 AX Advisory 기회 진단",
                    "textStyle": {
                      "color": "#d7e0ea"
                    }
                  }
                ]
              }
            ]
          }
        }
      ]
    },
    "visualContainerObjects": {
      "background": [
        {
          "properties": {
            "show": {
              "expr": {
                "Literal": {
                  "Value": "false"
                }
              }
            }
          }
        }
      ]
    },
    "drillFilterOtherVisuals": true
  }
}